splatnet3_scraper/__init__.py
splatnet3_scraper/auth/__init__.py
splatnet3_scraper/auth/exceptions.py
splatnet3_scraper/auth/graph_ql_queries.py
splatnet3_scraper/auth/nso.py
splatnet3_scraper/auth/tokens/__init__.py
splatnet3_scraper/auth/tokens/constructor.py
splatnet3_scraper/auth/tokens/environment_manager.py
splatnet3_scraper/auth/tokens/keychain.py
splatnet3_scraper/auth/tokens/manager.py
splatnet3_scraper/auth/tokens/regenerator.py
splatnet3_scraper/auth/tokens/token_typing.py
splatnet3_scraper/auth/tokens/tokens.py
splatnet3_scraper/constants.py
splatnet3_scraper/query/__init__.py
splatnet3_scraper/query/config/__init__.py
splatnet3_scraper/query/config/callbacks.py
splatnet3_scraper/query/config/config.py
splatnet3_scraper/query/config/config_option.py
splatnet3_scraper/query/config/config_option_handler.py
splatnet3_scraper/query/handler.py
splatnet3_scraper/query/json_parser.py
splatnet3_scraper/query/responses.py
splatnet3_scraper/scraper/__init__.py
splatnet3_scraper/scraper/main.py
splatnet3_scraper/scraper/query_map.py
splatnet3_scraper/splatnet3_webview_data.json
splatnet3_scraper/tournament_webview_data.json
splatnet3_scraper/utils/__init__.py
splatnet3_scraper/utils/hash_data.py
splatnet3_scraper/utils/json_helpers.py
splatnet3_scraper/utils/retry.py
splatnet3_scraper-1.1.5.dist-info/METADATA
splatnet3_scraper-1.1.5.dist-info/WHEEL
splatnet3_scraper-1.1.5.dist-info/RECORD
