Metadata-Version: 2.1
Name: splatnet3_scraper
Version: 1.1.5
Summary: Scraper for SplatNet 3 for Splatoon 3
License: GPL-3.0-or-later
Author: Cesar E Garza
Author-email: cesar@cegarza.com
Requires-Python: >=3.10,<4.0
Classifier: License :: OSI Approved :: GNU General Public License v3 or later (GPLv3+)
Classifier: Programming Language :: Python :: 3
Classifier: Programming Language :: Python :: 3.10
Classifier: Programming Language :: Python :: 3.11
Classifier: Programming Language :: Python :: 3.12
Classifier: Programming Language :: Python :: 3.13
Provides-Extra: all
Provides-Extra: examples
Provides-Extra: parquet
Requires-Dist: pandas[examples] (>=1.5.3,<2.0.0) ; extra == "examples"
Requires-Dist: psycopg2[examples] (>=2.9.5,<3.0.0) ; extra == "examples"
Requires-Dist: requests (>=2.28.1,<3.0.0)
Requires-Dist: sqlalchemy[examples] (>=2.0.1,<3.0.0) ; extra == "examples"
